citnps
