Metadata-Version: 2.1
Name: citnps
Version: 0.0.2
Summary: Camera Is The New Piezoelectric Sensor
Home-page: UNKNOWN
Author: Cossart Team
Author-email: julien.denis3@gmail.com
License: UNKNOWN
Project-URL: Bug Reports, https://gitlab.com/cossartlab/citnps/-/issues
Project-URL: Source, https://gitlab.com/cossartlab/citnps
Keywords: CITNPS
Platform: UNKNOWN
Classifier: Development Status :: 3 - Alpha
Classifier: Intended Audience :: Science/Research
Classifier: License :: OSI Approved :: MIT License
Classifier: Programming Language :: Python :: 3.6
Classifier: Programming Language :: Python :: 3.7
Requires-Python: >=3.5, <4
